<?xml version="1.0" encoding="utf-8"?>
<componentDescriptor version="1.0">
	<componentName>Image</componentName>
	<as2Url>as2/org.silex.ui.players.Audio.swf</as2Url>
	<html5Url>html5#org.silex.ui.Audio</html5Url>
	<className>org.silex.ui.players.Audio</className>
	<specificEditorUrl>editors/Audio.swf</specificEditorUrl>
	<parentDescriptorClassName>flash.MovieClip</parentDescriptorClassName>
	<componentRoot>main</componentRoot>
	<metaData>
	<pluginRelativeUrl>plugins/baseComponents/</pluginRelativeUrl>
		<addComponentParams>
			<name>Audio</name>
			<uid>silex.AddComponent.ToolItem.AddAudio</uid>
			<groupUid>silex.AddComponent.ToolItemGroup.AudioVideo</groupUid>
			<toolUid>silex.AddComponent.Tool</toolUid>
			<label>LABEL_AUDIO</label>
			<description>DESCRIPTION_AUDIO</description>
			<level>1</level>
			<action>addMediaComponent</action>
			<initPropertyName>url</initPropertyName>
			<iconUrl>icons/mp3.swf</iconUrl>
		</addComponentParams>
	</metaData>
	<properties>
		<autoPlay>
			<type>Boolean</type>
			<description>PROPERTIES_LABEL_AUTOPLAY</description>
			<defaultValue>true</defaultValue>
			<isRegistered>true</isRegistered>
			<group>parameters</group>
		</autoPlay>		
		<loop>
			<type>Boolean</type>
			<description>PROPERTIES_LABEL_AUTOREPLAY</description>
			<defaultValue>false</defaultValue>
			<isRegistered>true</isRegistered>
			<group>parameters</group>
		</loop>		
		<showNavigation>
			<type>Boolean</type>
			<description>PROPERTIES_LABEL_SHOW_UI</description>
			<defaultValue>true</defaultValue>
			<isRegistered>true</isRegistered>
			<group>parameters</group>
		</showNavigation>		
		<mute>
			<type>Boolean</type>
			<description>PROPERTIES_LABEL_IS_MUTED</description>
			<defaultValue>false</defaultValue>
			<isRegistered>true</isRegistered>
			<group>parameters</group>
		</mute>		
		<url>
			<type>String</type>
			<subType>Url</subType>
			<description>PROPERTIES_LABEL_URL</description>
			<defaultValue>defaultUrl</defaultValue>
			<isRegistered>true</isRegistered>
			<extensions>mp3</extensions>
			<group>attributes</group>			
		</url>	
		<volume>
			<type>Float</type>
			<minValue>1</minValue>
			<maxValue>100</maxValue>
			<description>PROPERTIES_LABEL_VOLUME_LEVEL</description>
			<defaultValue>50</defaultValue>
			<isRegistered>true</isRegistered>
			<group>parameters</group>			
		</volume>
		<clickable>
			<type>Boolean</type>
			<description>PROPERTIES_LABEL_SHOW_HAND_ON_ROLLOVER</description>
			<defaultValue>false</defaultValue>
			<isRegistered>true</isRegistered>
			<group>attributes</group>
		</clickable>		
	</properties>
</componentDescriptor>