<?xml version="1.0" encoding="UTF-8"?><element type_str="object" name_str="root"><element type_str="string" name_str="title"><![CDATA[demo.video]]></element><element type_str="string" name_str="deeplink"><![CDATA[start/demo.video]]></element><element type_str="string" name_str="pubDate"><![CDATA[Wed Oct 20 22:20:20 GMT+0200 2010]]></element><element type_str="string" name_str="urlBase"><![CDATA[http://localhost:8888/silex/trunk/silex_server/coming.soon/]]></element><element type_str="object" name_str="content"><element type_str="object" name_str="0"><element type_str="string" name_str="context"><![CDATA[*]]></element><element type_str="string" name_str="text"><![CDATA[ <object width="100%" height="100%"><param name="movie" value="http://www.dailymotion.com/swf/video/xel08e?width=480&iframe=0&additionalInfos=0&autoPlay=0&hideInfos=0"></param><param name="allowFullScreen" value="true"></param><param name="allowScriptAccess" value="always"></param><embed type="application/x-shockwave-flash" src="http://www.dailymotion.com/swf/video/xel08e?width=480&iframe=0&additionalInfos=0&autoPlay=0&hideInfos=0" width="100%" height="100%" allowfullscreen="true" allowscriptaccess="always"></embed></object>]]></element></element><element type_str="object" name_str="1"><element type_str="string" name_str="context"><![CDATA[*]]></element><element type_str="string" name_str="htmlEquivalent"><![CDATA[<object classid="clsid:d27cdb6e-ae6d-11cf-96b8-444553540000" codebase="http://fpdownload.macromedia.com/pub/shockwave/cabs/flash/swflash.cab#version=8,0,0,0" width="780.5" height="91.2" ><param name="movie" value="../../../media/coming.soon/design/screencast-of-the-latest.swf" /><param name="quality" value="best" /><param name="bgcolor" value="#323232" /><embed src = "../../../media/coming.soon/design/screencast-of-the-latest.swf" quality = "best" bgcolor = "#323232" width = "780.5" height = "91.2" type = "application/x-shockwave-flash" pluginspage = "http://www.macromedia.com/go/getflashplayer" /></object>]]></element></element><element type_str="object" name_str="2"><element type_str="string" name_str="context"><![CDATA[*]]></element><element type_str="string" name_str="text"><![CDATA[label]]></element><element type_str="string" name_str="htmlEquivalent"><![CDATA[<p>label</p>]]></element></element></element></element>